galaxy/__init__.py
galaxy/py.typed
galaxy/tours/__init__.py
galaxy/tours/_impl.py
galaxy/tours/_interface.py
galaxy/tours/_schema.py
galaxy/tours/validate.py
galaxy_tours-25.0.3.dist-info/METADATA
galaxy_tours-25.0.3.dist-info/WHEEL
galaxy_tours-25.0.3.dist-info/entry_points.txt
galaxy_tours-25.0.3.dist-info/top_level.txt
galaxy_tours-25.0.3.dist-info/RECORD
